odoo/addons/base_ical/README.rst
odoo/addons/base_ical/__init__.py
odoo/addons/base_ical/__manifest__.py
odoo/addons/base_ical/controllers/__init__.py
odoo/addons/base_ical/controllers/main.py
odoo/addons/base_ical/demo/base_ical.xml
odoo/addons/base_ical/i18n/.empty
odoo/addons/base_ical/i18n/base_ical.pot
odoo/addons/base_ical/models/__init__.py
odoo/addons/base_ical/models/base_ical.py
odoo/addons/base_ical/models/base_ical_url_description.py
odoo/addons/base_ical/models/base_ical_url_show.py
odoo/addons/base_ical/models/res_users.py
odoo/addons/base_ical/readme/CONFIGURE.rst
odoo/addons/base_ical/readme/CONTRIBUTORS.rst
odoo/addons/base_ical/readme/DESCRIPTION.rst
odoo/addons/base_ical/readme/ROADMAP.rst
odoo/addons/base_ical/readme/USAGE.rst
odoo/addons/base_ical/security/ir.model.access.csv
odoo/addons/base_ical/static/description/icon.png
odoo/addons/base_ical/static/description/index.html
odoo/addons/base_ical/tests/__init__.py
odoo/addons/base_ical/tests/test_base_ical.py
odoo/addons/base_ical/views/base_ical.xml
odoo/addons/base_ical/views/res_users.xml
odoo_addon_base_ical-15.0.1.0.0.3.dist-info/METADATA
odoo_addon_base_ical-15.0.1.0.0.3.dist-info/WHEEL
odoo_addon_base_ical-15.0.1.0.0.3.dist-info/top_level.txt
odoo_addon_base_ical-15.0.1.0.0.3.dist-info/RECORD
