Metadata-Version: 2.1
Name: odoo-addon-base-ical
Version: 15.0.1.0.0.3
Summary: Provide (readonly) .ics URLs to calendar-like models
Home-page: https://github.com/OCA/server-backend
Author: Hunki Enterprises BV, Odoo Community Association (OCA)
Author-email: support@odoo-community.org
License: AGPL-3
Platform: UNKNOWN
Classifier: Programming Language :: Python
Classifier: Framework :: Odoo
Classifier: Framework :: Odoo :: 15.0
Classifier: License :: OSI Approved :: GNU Affero General Public License v3
Classifier: Development Status :: 3 - Alpha
Requires-Python: >=3.8
Requires-Dist: odoo <15.1dev,>=15.0a
Requires-Dist: vobject
